rc_openapi_sdk/__init__.py
rc_openapi_sdk/core.py
rc_openapi_sdk-1.16.3.dist-info/LICENSE
rc_openapi_sdk-1.16.3.dist-info/METADATA
rc_openapi_sdk-1.16.3.dist-info/WHEEL
rc_openapi_sdk-1.16.3.dist-info/top_level.txt
rc_openapi_sdk-1.16.3.dist-info/RECORD
