Metadata-Version: 2.1
Name: rc-openapi-sdk
Version: 1.16.3
Summary: OpenAPI SDK for Python ~ 融创API开放平台所用
Home-page: https://github.com/Haoke98/openapi-sdk
Author: Sadam·Sadik
Author-email: Haoke98@outlook.com
License: UNKNOWN
Platform: UNKNOWN
Classifier: Programming Language :: Python :: 3
Classifier: License :: OSI Approved :: MIT License
Classifier: Operating System :: OS Independent
Requires-Python: >=3.6
Requires-Dist: requests (>=2.25.1)
Requires-Dist: pycryptodome (>=3.9.0)
Requires-Dist: python-dateutil (>=2.8.1)
Requires-Dist: urllib3 (>=1.26.0)
Requires-Dist: certifi (>=2020.12.5)
